mmio/__init__.py
mmio/mio.py
mmio-0.1.0.dist-info/LICENSE
mmio-0.1.0.dist-info/METADATA
mmio-0.1.0.dist-info/WHEEL
mmio-0.1.0.dist-info/top_level.txt
mmio-0.1.0.dist-info/RECORD
